staplesremoval/__init__.py
staplesremoval/data.py
staplesremoval/detect_infection.py
staplesremoval/inpainting.py
staplesremoval/remove_staples.py
staplesremoval/staples_detector.py
staplesremoval/trapezoidal_fuzzy_color_segmentation.py
staplesremoval/triangular_fuzzy_color_segmentation.py
staplesremoval/images/image_infection.png
staplesremoval/images/image_noinfection.png
staplesremoval-1.7.dist-info/LICENSE.txt
staplesremoval-1.7.dist-info/METADATA
staplesremoval-1.7.dist-info/WHEEL
staplesremoval-1.7.dist-info/top_level.txt
staplesremoval-1.7.dist-info/RECORD
