Metadata-Version: 2.1
Name: staplesremoval
Version: 1.7
Summary: Algorithm for staple detection and mask generation
Home-page: https://github.com/mmunar97
Author: marcmunar
Author-email: marc.munar1@estudiant.uib.es
License: mit
Platform: UNKNOWN
Requires-Dist: matplotlib
Requires-Dist: scipy
Requires-Dist: scikit-image
Requires-Dist: softcolor
